flask_flaskwork.py
setup.py
flask_flaskwork.egg-info/PKG-INFO
flask_flaskwork.egg-info/SOURCES.txt
flask_flaskwork.egg-info/dependency_links.txt
flask_flaskwork.egg-info/not-zip-safe
flask_flaskwork.egg-info/requires.txt
flask_flaskwork.egg-info/top_level.txt