Metadata-Version: 1.0
Name: flask-flaskwork
Version: 0.1.11
Summary: A Flask plugin to talk with the Flaskwork Chrome extension.
Home-page: UNKNOWN
Author: Tim Radke
Author-email: tim.is@self-proclaimed.ninja
License: BSD
Platform: UNKNOWN
